[
  {
    "src": "/assets/dental/d1-1.jpg",
    "alt": "Center For Pediatric Dentistry",
    "area": "Center For Pediatric Dentistry",
    "address": "La Habra, California",
    "href": "/cfpdlh"
  },
  {
    "src": "/assets/dental/d2-1.jpg",
    "alt": "Edna Cuevas, DDs",
    "area": "Edna Cuevas, DDs",
    "address": "Covina, California",
    "href": "/ecddc"
  },
  {
    "src": "/assets/dental/d3-1.jpg",
    "alt": "Comfort Dental",
    "area": "Comfort Dental",
    "address": "Pasadena, California",
    "href": "/cdp"
  },
  {
    "src": "/assets/dental/d4-1.jpg",
    "alt": "Lincoln Dental",
    "area": "Lincoln Dental",
    "address": "Pasadena, California",
    "href": "/ldp"
  },
  {
    "src": "/assets/dental/d5-1.jpg",
    "alt": "Access Dental",
    "area": "Access Dental",
    "address": "West Covina, California",
    "href": "/adw"
  },
  {
    "src": "/assets/dental/d6-1.jpg",
    "alt": "Redlands Family Dental",
    "area": "Redlands Family Dental",
    "address": "Redlands, California"
  },
  {
    "src": "/assets/dental/d7-1.jpg",
    "alt": "Shodhan Dentistry",
    "area": "Shodhan Dentistry",
    "address": "Desert Hot Springs, California"
  },
  {
    "src": "/assets/dental/d8-1.jpg",
    "alt": "Dental Care of Chino Hills",
    "area": "Dental Care of Chino Hills",
    "address": "Chino Hills, California"
  },
  {
    "src": "/assets/dental/d9-1.jpg",
    "alt": "Rosetta Vergel De Dios DMD INC.",
    "area": "Rosetta Vergel De Dios, DMD Inc.",
    "address": "Anaheim, California"
  },
  {
    "src": "/assets/dental/d10-1.jpg",
    "alt": "Orlando Vales, DDs, Inc.",
    "area": "Orlando Vales, DDs, Inc.",
    "address": "West Covina, California"
  },
  {
    "src": "/assets/dental/d11-1.jpg",
    "alt": "Synergy Dental Implant",
    "area": "Synergy Dental Implant",
    "address": "West Covina, California"
  },
  {
    "src": "/assets/dental/d12-1.png",
    "alt": "Max Mosslehi, D.M.D., Inc.",
    "area": "Max Mosslehi, D.M.D., Inc.",
    "address": "Tustin, California"
  }
]
