[
  {
    "src": "/assets/hospitality/h1-1.jpeg",
    "alt": "Nabemono Shabushabu",
    "area": "Nabemono Shabushabu",
    "address": "Alhambra, California"
  },
  {
    "src": "/assets/hospitality/h2-1.jpg",
    "alt": "Hong Kong Express",
    "area": "Hong Kong Express",
    "address": "Orange, California"
  },
  {
    "src": "/assets/hospitality/h3-1.jpg",
    "alt": "Panda Wok",
    "area": "Panda Wok",
    "address": "Orange, California"
  },
  {
    "src": "/assets/hospitality/h4-1.jpg",
    "alt": "Fortune Cookies Chinese Bistro",
    "area": "Fortune Cookies Chinese Bistro",
    "address": "Laguna Wood, California"
  },
  {
    "src": "/assets/hospitality/h5-1.jpeg",
    "alt": "Pick a Poke",
    "area": "Pick a Poke",
    "address": "South Gate, California"
  }
]
